[
    {
      "id": "0",
      "name": "UltraBoots ",
      "category": "Womens Running",
      "imageUrl": [
        "https://i.pinimg.com/236x/88/0a/dd/880add7ef4ae62f1857e893484e7ca89.jpg"
      ],
      "oldPrice":"189.00",
      "sizes":[
        {"size":"6.0","isSelected":false},
        {"size":"6.5","isSelected":false},
        {"size":"7.0","isSelected":false},
        {"size":"7.5","isSelected":false},
        {"size":"8.0","isSelected":false},
        {"size":"8.5","isSelected":false},
        {"size":"9.0","isSelected":false}
  
  
      ],
      "price":"79.00",
      "description":"put some pep in your step",
      "title":"Adidas Running Shoes "
    },
    {
      "id": "1",
      "name": "UltraBoots ",
      "category": "Womens Running",
      "imageUrl": [
        "https://i.pinimg.com/236x/31/2e/06/312e064407488e61406826a4a402af48.jpg"
      ],
      "oldPrice":"189.00",
      "sizes":[
        {"size":"6.0","isSelected":false},
        {"size":"6.5","isSelected":false},
        {"size":"7.0","isSelected":false},
        {"size":"7.5","isSelected":false},
        {"size":"8.0","isSelected":false},
        {"size":"8.5","isSelected":false},
        {"size":"9.0","isSelected":false}
  
  
      ],
      "price":"79.00",
      "description":"put some pep in your step",
      "title":"Adidas Running Shoes "
    },
    {
      "id": "2",
      "name": "UltraBoots ",
      "category": "Womens Running",
      "imageUrl": [
        "https://i.pinimg.com/236x/5c/f1/93/5cf1935dc7bb652429f732cf86711352.jpg"
      ],
      "oldPrice":"189.00",
      "sizes":[
        {"size":"6.0","isSelected":false},
        {"size":"6.5","isSelected":false},
        {"size":"7.0","isSelected":false},
        {"size":"7.5","isSelected":false},
        {"size":"8.0","isSelected":false},
        {"size":"8.5","isSelected":false},
        {"size":"9.0","isSelected":false}
  
  
      ],
      "price":"30.00",
      "description":"put some pep in your step",
      "title":"Adidas Running Shoes "
    },
    {
      "id": "3",
      "name": "UltraBoots ",
      "category": "Womens Running",
      "imageUrl": [
        "https://i.pinimg.com/236x/bc/2d/38/bc2d38a4385b0aefde9dd0200589caaf.jpg"
      ],
      "oldPrice":"189.00",
      "sizes":[
        {"size":"6.0","isSelected":false},
        {"size":"6.5","isSelected":false},
        {"size":"7.0","isSelected":false},
        {"size":"7.5","isSelected":false},
        {"size":"8.0","isSelected":false},
        {"size":"8.5","isSelected":false},
        {"size":"9.0","isSelected":false}
  
  
      ],
      "price":"60.00",
      "description":"put some pep in your step",
      "title":"Adidas Running Shoes "
    },
    {
      "id": "4",
      "name": "UltraBoots ",
      "category": "Womens Running",
      "imageUrl": [
        "https://i.pinimg.com/474x/9f/80/ad/9f80adf3216442572a57e982cc87cceb.jpg"
      ],
      "oldPrice":"189.00",
      "sizes":[
        {"size":"6.0","isSelected":false},
        {"size":"6.5","isSelected":false},
        {"size":"7.0","isSelected":false},
        {"size":"7.5","isSelected":false},
        {"size":"8.0","isSelected":false},
        {"size":"8.5","isSelected":false},
        {"size":"9.0","isSelected":false}
  
  
      ],
      "price":"60.00",
      "description":"put some pep in your step",
      "title":"Adidas Running Shoes "
    },
    {
      "id": "5",
      "name": "UltraBoots ",
      "category": "Womens Running",
      "imageUrl": [
        "https://i.pinimg.com/236x/e9/ce/5e/e9ce5e7d1773d79f7bf8cd26d9337efd.jpg"
      ],
      "oldPrice":"189.00",
      "sizes":[
        {"size":"6.0","isSelected":false},
        {"size":"6.5","isSelected":false},
        {"size":"7.0","isSelected":false},
        {"size":"7.5","isSelected":false},
        {"size":"8.0","isSelected":false},
        {"size":"8.5","isSelected":false},
        {"size":"9.0","isSelected":false}
  
  
      ],
      "price":"60.00",
      "description":"put some pep in your step",
      "title":"Adidas Running Shoes "
    },
    {
      "id": "6",
      "name": "UltraBoots ",
      "category": "Womens Running",
      "imageUrl": [
        "https://i.pinimg.com/236x/37/a8/2f/37a82fbc16bdd9abe6279a5afe229c1b.jpg"
        
      ],
      "oldPrice":"189.00",
      "sizes":[
        {"size":"6.0","isSelected":false},
        {"size":"6.5","isSelected":false},
        {"size":"7.0","isSelected":false},
        {"size":"7.5","isSelected":false},
        {"size":"8.0","isSelected":false},
        {"size":"8.5","isSelected":false},
        {"size":"9.0","isSelected":false}
  
  
      ],
      "price":"60.00",
      "description":"put some pep in your step",
      "title":"Adidas Running Shoes "
    }
    ,
    {
      "id": "6",
      "name": "Womens ",
      "category": "Womens Running",
      "imageUrl": [
        "https://i.pinimg.com/236x/20/91/7c/20917c84d3e83cbcd5a9fced576f6e1f.jpg"
        
      ],
      "oldPrice":"189.00",
      "sizes":[
        {"size":"6.0","isSelected":false},
        {"size":"6.5","isSelected":false},
        {"size":"7.0","isSelected":false},
        {"size":"7.5","isSelected":false},
        {"size":"8.0","isSelected":false},
        {"size":"8.5","isSelected":false},
        {"size":"9.0","isSelected":false}
  
  
      ],
      "price":"60.00",
      "description":"put some pep in your step",
      "title":"Adidas Running Shoes "
    }
  
  ]